testlite/TestLite.py
testlite/_Testlite.py
testlite/__init__.py
testlite/_config.py
testlite/_helper.py
testlite/_models.py
testlite/_reports.py
testlite/_serializers.py
testlite_pytest/__init__.py
testlite_pytest/plugin.py
TestLitePytest-0.3.0.dist-info/LICENSE
TestLitePytest-0.3.0.dist-info/METADATA
TestLitePytest-0.3.0.dist-info/WHEEL
TestLitePytest-0.3.0.dist-info/entry_points.txt
TestLitePytest-0.3.0.dist-info/top_level.txt
TestLitePytest-0.3.0.dist-info/RECORD
