Metadata-Version: 2.1
Name: TestLitePytest
Version: 0.3.0
Summary: Pytest adaptor for TestLite TMS system
Author: Dmitry Skryabin
Author-email: Dmitry Skryabin <skryabind98@gmail.com>
Maintainer-email: Dmitry Skryabin <skryabind98@gmail.com>
License: 
Project-URL: Repository, https://github.com/DmitrySkryabin/TestLitePytest
Project-URL: TestLite, https://github.com/DmitrySkryabin/TestLite
Classifier: Framework :: Pytest
Classifier: Development Status :: 4 - Beta
Classifier: Intended Audience :: Developers
Classifier: Topic :: Software Development :: Testing
Classifier: Operating System :: OS Independent
Classifier: Programming Language :: Python
Classifier: Programming Language :: Python :: 3.8
Classifier: Programming Language :: Python :: 3.9
Classifier: Programming Language :: Python :: 3.10
Classifier: Programming Language :: Python :: 3.11
Classifier: Programming Language :: Python :: 3.12
Classifier: Programming Language :: Python :: 3 :: Only
Classifier: Programming Language :: Python :: Implementation :: CPython
Classifier: Programming Language :: Python :: Implementation :: PyPy
Classifier: License :: OSI Approved :: MIT License
Classifier: Framework :: Pytest
Requires-Python: >=3.10
License-File: LICENSE
Requires-Dist: pytest>=8.3.2
Requires-Dist: requests>=2.32.3
